lecture_transcriber/__init__.py
lecture_transcriber/__main__.py
lecture_transcriber/preprocess_audio.py
lecture_transcriber/transcribe.py
lecture_transcriber/utils.py
lecture_transcriber-0.4.1.dist-info/LICENSE
lecture_transcriber-0.4.1.dist-info/WHEEL
lecture_transcriber-0.4.1.dist-info/METADATA
lecture_transcriber-0.4.1.dist-info/RECORD
