Metadata-Version: 2.1
Name: lecture-transcriber
Version: 0.4.1
Summary: A DeepSpeech-based transcriber using DeepSegment to separate sentences in a long audio recording.
License: BSD-3-Clause
Author: Harrison Morgan
Author-email: harrison.morgan@gmail.com
Requires-Python: >=3.7,<4.0
Classifier: License :: OSI Approved :: BSD License
Classifier: Programming Language :: Python :: 3
Classifier: Programming Language :: Python :: 3.7
Classifier: Programming Language :: Python :: 3.8
Requires-Dist: deepsegment (==2.3.0)
Requires-Dist: deepspeech (==0.6.1)
Requires-Dist: pydub (>=0.23,<0.24)
Requires-Dist: sox (==1.3.7)
Requires-Dist: tensorflow (>=2.2.0,<3.0.0)
Requires-Dist: tqdm (>=4,<5)
